resql/__init__.py
resql/core/errors.py
resql/core/resql.py
resql-0.1.5.dist-info/LICENSE
resql-0.1.5.dist-info/WHEEL
resql-0.1.5.dist-info/METADATA
resql-0.1.5.dist-info/RECORD
