Metadata-Version: 2.1
Name: resql
Version: 0.1.5
Summary: A beginner friendly database
Home-page: https://github.com/ResetXD/resql
Author: ResetXD
Author-email: resetwastakenwastaken@gmail.com
Requires-Python: >=3.8,<4.0
Classifier: Programming Language :: Python :: 3
Classifier: Programming Language :: Python :: 3.10
Classifier: Programming Language :: Python :: 3.8
Classifier: Programming Language :: Python :: 3.9
Project-URL: Repository, https://github.com/ResetXD/resql
